{
  "key": "live:matches:2026-06-19",
  "value": {
    "source": "local-fallback",
    "updatedAt": "2026-06-13T18:01:16.492Z",
    "date": "2026-06-19",
    "total": 8,
    "data": [
      {
        "id": "match-003",
        "matchNumber": 3,
        "stage": "group_stage",
        "group": "A",
        "round": "R2",
        "date": "2026-06-18",
        "kickoffLocal": "12:00",
        "timezone": "America/New_York",
        "homeTeamId": "czech-republic",
        "awayTeamId": "south-africa",
        "homeTeamName": "Czech Republic",
        "awayTeamName": "South Africa",
        "homeTeamCode": "CZE",
        "awayTeamCode": "RSA",
        "stadiumId": "mercedes-benz",
        "stadiumName": "Mercedes-Benz Stadium",
        "city": "Atlanta",
        "country": "Estados Unidos",
        "status": "scheduled",
        "homeScore": null,
        "awayScore": null,
        "minute": null,
        "penalties": null
      },
      {
        "id": "match-004",
        "matchNumber": 4,
        "stage": "group_stage",
        "group": "A",
        "round": "R2",
        "date": "2026-06-18",
        "kickoffLocal": "19:00",
        "timezone": "America/Mexico_City",
        "homeTeamId": "mexico",
        "awayTeamId": "south-korea",
        "homeTeamName": "Mexico",
        "awayTeamName": "Korea Republic",
        "homeTeamCode": "MEX",
        "awayTeamCode": "KOR",
        "stadiumId": "akron",
        "stadiumName": "Estadio Akron",
        "city": "Guadalajara",
        "country": "México",
        "status": "scheduled",
        "homeScore": null,
        "awayScore": null,
        "minute": null,
        "penalties": null
      },
      {
        "id": "match-009",
        "matchNumber": 9,
        "stage": "group_stage",
        "group": "B",
        "round": "R2",
        "date": "2026-06-18",
        "kickoffLocal": "12:00",
        "timezone": "America/Los_Angeles",
        "homeTeamId": "switzerland",
        "awayTeamId": "bosnia-herzegovina",
        "homeTeamName": "Switzerland",
        "awayTeamName": "Bosnia and Herzegovina",
        "homeTeamCode": "SUI",
        "awayTeamCode": "BIH",
        "stadiumId": "sofi",
        "stadiumName": "SoFi Stadium",
        "city": "Inglewood",
        "country": "Estados Unidos",
        "status": "scheduled",
        "homeScore": null,
        "awayScore": null,
        "minute": null,
        "penalties": null
      },
      {
        "id": "match-010",
        "matchNumber": 10,
        "stage": "group_stage",
        "group": "B",
        "round": "R2",
        "date": "2026-06-18",
        "kickoffLocal": "15:00",
        "timezone": "America/Vancouver",
        "homeTeamId": "canada",
        "awayTeamId": "qatar",
        "homeTeamName": "Canada",
        "awayTeamName": "Qatar",
        "homeTeamCode": "CAN",
        "awayTeamCode": "QAT",
        "stadiumId": "bc-place",
        "stadiumName": "BC Place",
        "city": "Vancouver",
        "country": "Canadá",
        "status": "scheduled",
        "homeScore": null,
        "awayScore": null,
        "minute": null,
        "penalties": null
      },
      {
        "id": "match-015",
        "matchNumber": 15,
        "stage": "group_stage",
        "group": "C",
        "round": "R2",
        "date": "2026-06-19",
        "kickoffLocal": "18:00",
        "timezone": "America/New_York",
        "homeTeamId": "scotland",
        "awayTeamId": "morocco",
        "homeTeamName": "Scotland",
        "awayTeamName": "Morocco",
        "homeTeamCode": "SCO",
        "awayTeamCode": "MAR",
        "stadiumId": "lincoln-financial",
        "stadiumName": "Lincoln Financial Field",
        "city": "Philadelphia",
        "country": "Estados Unidos",
        "status": "scheduled",
        "homeScore": null,
        "awayScore": null,
        "minute": null,
        "penalties": null
      },
      {
        "id": "match-016",
        "matchNumber": 16,
        "stage": "group_stage",
        "group": "C",
        "round": "R2",
        "date": "2026-06-19",
        "kickoffLocal": "21:00",
        "timezone": "America/New_York",
        "homeTeamId": "brazil",
        "awayTeamId": "haiti",
        "homeTeamName": "Brazil",
        "awayTeamName": "Haiti",
        "homeTeamCode": "BRA",
        "awayTeamCode": "HAI",
        "stadiumId": "gillette",
        "stadiumName": "Gillette Stadium",
        "city": "Foxborough",
        "country": "Estados Unidos",
        "status": "scheduled",
        "homeScore": null,
        "awayScore": null,
        "minute": null,
        "penalties": null
      },
      {
        "id": "match-021",
        "matchNumber": 21,
        "stage": "group_stage",
        "group": "D",
        "round": "R2",
        "date": "2026-06-19",
        "kickoffLocal": "21:00",
        "timezone": "America/Los_Angeles",
        "homeTeamId": "turkiye",
        "awayTeamId": "paraguay",
        "homeTeamName": "Türkiye",
        "awayTeamName": "Paraguay",
        "homeTeamCode": "TUR",
        "awayTeamCode": "PAR",
        "stadiumId": "levis",
        "stadiumName": "Levi's Stadium",
        "city": "Santa Clara",
        "country": "Estados Unidos",
        "status": "scheduled",
        "homeScore": null,
        "awayScore": null,
        "minute": null,
        "penalties": null
      },
      {
        "id": "match-022",
        "matchNumber": 22,
        "stage": "group_stage",
        "group": "D",
        "round": "R2",
        "date": "2026-06-19",
        "kickoffLocal": "12:00",
        "timezone": "America/Los_Angeles",
        "homeTeamId": "united-states",
        "awayTeamId": "australia",
        "homeTeamName": "United States",
        "awayTeamName": "Australia",
        "homeTeamCode": "USA",
        "awayTeamCode": "AUS",
        "stadiumId": "lumen",
        "stadiumName": "Lumen Field",
        "city": "Seattle",
        "country": "Estados Unidos",
        "status": "scheduled",
        "homeScore": null,
        "awayScore": null,
        "minute": null,
        "penalties": null
      }
    ]
  },
  "createdAt": "2026-06-13T18:01:16.492Z",
  "expiresAt": 9007199254740991
}